era5_ml.py
era5_pl.py
era5_sfc.py
grib2nc.py
fall3dutil/__init__.py
fall3dutil/configuration.py
fall3dutil/ecmwf.py
fall3dutil/grib_filter.py
fall3dutil-2.2.dist-info/licenses/LICENSE
fall3dutil-2.2.dist-info/METADATA
fall3dutil-2.2.dist-info/WHEEL
fall3dutil-2.2.dist-info/top_level.txt
fall3dutil-2.2.dist-info/RECORD
