Metadata-Version: 2.4
Name: fall3dutil
Version: 2.2
Summary: Utilities for the FALL3D model
Author-email: Leonardo Mingari <lmingari@gmail.com>
License: MIT License
Project-URL: repository, https://github.com/lmingari/fall3dutil
Classifier: Programming Language :: Python :: 3
Classifier: License :: OSI Approved :: MIT License
Classifier: Operating System :: OS Independent
Requires-Python: >=3.7
License-File: LICENSE
Requires-Dist: datetime
Requires-Dist: configparser
Requires-Dist: requests
Requires-Dist: cdsapi
Requires-Dist: zipfile
Requires-Dist: logging
Provides-Extra: test
Requires-Dist: argparse; extra == "test"
Dynamic: license-file
